emcee/__init__.py
emcee/autocorr.py
emcee/emcee_version.py
emcee/ensemble.py
emcee/interruptible_pool.py
emcee/model.py
emcee/mpi_pool.py
emcee/pbar.py
emcee/ptsampler.py
emcee/state.py
emcee/utils.py
emcee/backends/__init__.py
emcee/backends/backend.py
emcee/backends/hdf.py
emcee/moves/__init__.py
emcee/moves/de.py
emcee/moves/de_snooker.py
emcee/moves/gaussian.py
emcee/moves/kde.py
emcee/moves/mh.py
emcee/moves/move.py
emcee/moves/red_blue.py
emcee/moves/stretch.py
emcee/moves/walk.py
emcee/tests/__init__.py
emcee/tests/integration/__init__.py
emcee/tests/integration/test_de.py
emcee/tests/integration/test_de_snooker.py
emcee/tests/integration/test_gaussian.py
emcee/tests/integration/test_kde.py
emcee/tests/integration/test_longdouble.py
emcee/tests/integration/test_proposal.py
emcee/tests/integration/test_stretch.py
emcee/tests/integration/test_walk.py
emcee/tests/unit/__init__.py
emcee/tests/unit/test_autocorr.py
emcee/tests/unit/test_backends.py
emcee/tests/unit/test_blobs.py
emcee/tests/unit/test_ensemble.py
emcee/tests/unit/test_sampler.py
emcee/tests/unit/test_state.py
emcee/tests/unit/test_stretch.py
emcee-3.1.5.dist-info/AUTHORS.rst
emcee-3.1.5.dist-info/LICENSE
emcee-3.1.5.dist-info/METADATA
emcee-3.1.5.dist-info/WHEEL
emcee-3.1.5.dist-info/top_level.txt
emcee-3.1.5.dist-info/RECORD
