Metadata-Version: 2.1
Name: emcee
Version: 3.1.5
Summary: The Python ensemble sampling toolkit for MCMC
Home-page: https://emcee.readthedocs.io
Author: Daniel Foreman-Mackey
Author-email: foreman.mackey@gmail.com
Maintainer: Daniel Foreman-Mackey
Maintainer-email: foreman.mackey@gmail.com
License: MIT
Project-URL: Source, https://github.com/dfm/emcee
Classifier: Development Status :: 5 - Production/Stable
Classifier: Intended Audience :: Developers
Classifier: Intended Audience :: Science/Research
Classifier: License :: OSI Approved :: MIT License
Classifier: Operating System :: OS Independent
Classifier: Programming Language :: Python
License-File: LICENSE
License-File: AUTHORS.rst
Requires-Dist: numpy
Provides-Extra: extras
Requires-Dist: h5py ; extra == 'extras'
Requires-Dist: scipy ; extra == 'extras'
Provides-Extra: tests
Requires-Dist: pytest ; extra == 'tests'
Requires-Dist: pytest-cov ; extra == 'tests'
Requires-Dist: coverage[toml] ; extra == 'tests'
